ainyan/__init__.py
ainyan/models.py
ainyan/mydatasets.py
ainyan/pdfcrawl.py
ainyan/query.py
ainyan/testc.py
ainyan/testd.py
ainyan/training.py
ainyan/zippers.py
ainyan-1.0.79.dist-info/LICENSE.txt
ainyan-1.0.79.dist-info/METADATA
ainyan-1.0.79.dist-info/WHEEL
ainyan-1.0.79.dist-info/entry_points.txt
ainyan-1.0.79.dist-info/top_level.txt
ainyan-1.0.79.dist-info/RECORD
