Metadata-Version: 2.1
Name: ainyan
Version: 1.0.79
Summary: Helpers for AI training
Author: Nicolas Modrzyk
Author-email: Nicolas Modrzyk <hellonico@gmail.com>
License: MIT License
Project-URL: Homepage, https://github.com/hellonico/ai.training
Keywords: feed,reader,tutorial
Classifier: License :: OSI Approved :: MIT License
Classifier: Programming Language :: Python
Classifier: Programming Language :: Python :: 3
Requires-Python: >=3.9
License-File: LICENSE.txt
Requires-Dist: setuptools ==68.2.2
Requires-Dist: datasets ==2.14.6
Requires-Dist: pandas ==2.1.0
Requires-Dist: boto3 ==1.28.*
Requires-Dist: python-docx ==1.0.1
Requires-Dist: Flask ==2.2.5
Requires-Dist: simplify-docx ==0.1.2
Requires-Dist: pypdf2 ==3.0.1
Requires-Dist: python-pptx ==0.6.22
Provides-Extra: dev
Requires-Dist: black ; extra == 'dev'
Requires-Dist: bumpver ; extra == 'dev'
Requires-Dist: isort ; extra == 'dev'
Requires-Dist: pip-tools ; extra == 'dev'
Requires-Dist: pytest ; extra == 'dev'
Requires-Dist: twine ; extra == 'dev'
